14           0 LOAD_CONST               1 ('')
              3 STORE_FAST               0 (_1)

 16           6 SETUP_LOOP             234 (to 243)
              9 LOAD_CONST               2 (102)
             12 LOAD_CONST               3 (114)
             15 LOAD_CONST               4 (111)
             18 LOAD_CONST               5 (109)
             21 LOAD_CONST               6 (32)
             24 LOAD_CONST               7 (122)
             27 LOAD_CONST               8 (108)
             30 LOAD_CONST               9 (105)
             33 LOAD_CONST              10 (98)
             36 LOAD_CONST               6 (32)
             39 LOAD_CONST               9 (105)
             42 LOAD_CONST               5 (109)
             45 LOAD_CONST              11 (112)
             48 LOAD_CONST               4 (111)
             51 LOAD_CONST               3 (114)
             54 LOAD_CONST              12 (116)
             57 LOAD_CONST               6 (32)
             60 LOAD_CONST              13 (100)
             63 LOAD_CONST              14 (101)
             66 LOAD_CONST              15 (99)
             69 LOAD_CONST               4 (111)
             72 LOAD_CONST               5 (109)
             75 LOAD_CONST              11 (112)
             78 LOAD_CONST               3 (114)
             81 LOAD_CONST              14 (101)
             84 LOAD_CONST              16 (115)
             87 LOAD_CONST              16 (115)
             90 LOAD_CONST               6 (32)
             93 LOAD_CONST              17 (97)
             96 LOAD_CONST              16 (115)
             99 LOAD_CONST               6 (32)
            102 LOAD_CONST              18 (121)
            105 LOAD_CONST              19 (10)
            108 LOAD_CONST               2 (102)
            111 LOAD_CONST               3 (114)
            114 LOAD_CONST               4 (111)
            117 LOAD_CONST               5 (109)
            120 LOAD_CONST               6 (32)
            123 LOAD_CONST              10 (98)
            126 LOAD_CONST               9 (105)
            129 LOAD_CONST              20 (110)
            132 LOAD_CONST              17 (97)
            135 LOAD_CONST              16 (115)
            138 LOAD_CONST              15 (99)
            141 LOAD_CONST               9 (105)
            144 LOAD_CONST               9 (105)
            147 LOAD_CONST               6 (32)
            150 LOAD_CONST               9 (105)
            153 LOAD_CONST               5 (109)
            156 LOAD_CONST              11 (112)
            159 LOAD_CONST               4 (111)
            162 LOAD_CONST               3 (114)
            165 LOAD_CONST              12 (116)
            168 LOAD_CONST               6 (32)
            171 LOAD_CONST              21 (117)
            174 LOAD_CONST              20 (110)
            177 LOAD_CONST              22 (104)
            180 LOAD_CONST              14 (101)
            183 LOAD_CONST              23 (120)
            186 LOAD_CONST               8 (108)
            189 LOAD_CONST               9 (105)
            192 LOAD_CONST               2 (102)
            195 LOAD_CONST              18 (121)
            198 LOAD_CONST               6 (32)
            201 LOAD_CONST              17 (97)
            204 LOAD_CONST              16 (115)
            207 LOAD_CONST               6 (32)
            210 LOAD_CONST              21 (117)
            213 BUILD_LIST              68

            /* 'from zlib import decompress as y\nfrom binascii import unhexlify as u' */

            216 GET_ITER            
        >>  217 FOR_ITER                22 (to 242)
            220 STORE_FAST               1 (i)

 17         223 LOAD_FAST                0 (_1)
            226 LOAD_NAME                0 (chr)
            229 LOAD_FAST                1 (i)
            232 CALL_FUNCTION            1
            235 INPLACE_ADD         
            236 STORE_FAST               0 (_1)
            239 JUMP_ABSOLUTE          217
        >>  242 POP_BLOCK           

            /* '_1 = from zlib import decompress as y\nfrom binascii import unhexlify as u' */

 18     >>  243 LOAD_FAST                0 (_1)
            246 LOAD_CONST               0 (None)
            249 DUP_TOP             
            250 EXEC_STMT       

            /* y = zlib.decompress; u = binascii.unhexlify*/    

 19         251 LOAD_CONST              24 (5225289992572816510375617297175513170291190435493698272730040307127264906868335001081343190341346338780406158345171271164984495365L)
            254 STORE_FAST               2 (c)

 20         257 LOAD_NAME                1 (eval)
            260 LOAD_NAME                2 (y)
            263 LOAD_NAME                3 (u)
            266 LOAD_NAME                4 (hex)
            269 LOAD_FAST                2 (c)
            272 CALL_FUNCTION            1
            275 LOAD_CONST              27 (2)
            278 LOAD_CONST              29 (-1)
            281 SLICE+3             
            282 CALL_FUNCTION            1
            285 CALL_FUNCTION            1
            288 CALL_FUNCTION            1
            291 STORE_FAST               3 (hi)

            /* eval(y(u(hex(c)[2:-1]))) */
            /* hi = eval(lambda x:x=='f51cbcad85917552208a18890b21ce9c') */

 21         294 LOAD_FAST                3 (hi)
            297 LOAD_NAME                5 (raw_input)
            300 LOAD_CONST              26 ('Your input:')
            303 CALL_FUNCTION            1
            306 CALL_FUNCTION            1
            309 PRINT_ITEM          
            310 PRINT_NEWLINE       
            311 LOAD_CONST               0 (None)
            314 RETURN_VALUE        

sha1() == 76a076d2d62274158245f7d5850493372801cddb
WhiteHat{76a076d2d62274158245f7d5850493372801cddb}